MANIFEST.in
README.rst
example_logistic.py
setup.py
pytron/__init__.py
pytron/tron.cpp
pytron/tron.pyx
pytron.egg-info/PKG-INFO
pytron.egg-info/SOURCES.txt
pytron.egg-info/dependency_links.txt
pytron.egg-info/top_level.txt
pytron/src/tron.cpp
pytron/src/tron.h
pytron/src/tron_helper.cpp
pytron/src/tron_helper.h
pytron/src/blas/blas.h
pytron/src/blas/blasp.h
pytron/src/blas/daxpy.c
pytron/src/blas/ddot.c
pytron/src/blas/dnrm2.c
pytron/src/blas/dscal.c