Metadata-Version: 1.1
Name: pytron
Version: 0.3
Summary: Python bindings for TRON optimizer
Home-page: http://pypi.python.org/pypi/pytron
Author: Fabian Pedregosa
Author-email: f@bianp.net
License: Simplified BSD
Platform: UNKNOWN
Classifier: Development Status :: 5 - Production/Stable
Classifier: Intended Audience :: Science/Research
Classifier: Intended Audience :: Developers
Classifier: License :: OSI Approved
Classifier: Programming Language :: Python
Classifier: Programming Language :: Python :: 2
Classifier: Programming Language :: Python :: 2.6
Classifier: Programming Language :: Python :: 2.7
Classifier: Programming Language :: Python :: 3
Classifier: Programming Language :: Python :: 3.2
Classifier: Programming Language :: Python :: 3.3
Classifier: Topic :: Software Development
Classifier: Operating System :: POSIX
Classifier: Operating System :: Unix
Requires: numpy
Requires: scipy
